qmeq/leadstun.py
qmeq/baths.py
qmeq/__init__.py
qmeq/indexing.py
qmeq/qdot.py
qmeq/wrappers/c_lapack.c
qmeq/wrappers/c_lapack.cpython-39-darwin.so
qmeq/wrappers/c_mytypes.pyx
qmeq/wrappers/__init__.py
qmeq/wrappers/c_lapack.pyx
qmeq/wrappers/mytypes.py
qmeq/wrappers/c_mytypes.cpython-39-darwin.so
qmeq/wrappers/c_mytypes.c
qmeq/tests/test_various.py
qmeq/tests/data_builder_elph.py
qmeq/tests/test_aprclass.py
qmeq/tests/test_leadstun.py
qmeq/tests/test_builder_elph.py
qmeq/tests/__init__.py
qmeq/tests/test_specfunc.py
qmeq/tests/test_indexing.py
qmeq/tests/data_builder.py
qmeq/tests/test_builder.py
qmeq/tests/test_qdot.py
qmeq/tests/test_baths.py
qmeq/approach/__init__.py
qmeq/approach/aprclass.py
qmeq/approach/c_kernel_handler.pyx
qmeq/approach/c_kernel_handler.c
qmeq/approach/kernel_handler.py
qmeq/approach/c_aprclass.pyx
qmeq/approach/c_aprclass.cpython-39-darwin.so
qmeq/approach/c_aprclass.c
qmeq/approach/c_kernel_handler.cpython-39-darwin.so
qmeq/approach/elph/c_redfield.c
qmeq/approach/elph/c_lindblad.pyx
qmeq/approach/elph/c_redfield.cpython-39-darwin.so
qmeq/approach/elph/neumann1.py
qmeq/approach/elph/c_pauli.cpython-39-darwin.so
qmeq/approach/elph/lindblad.py
qmeq/approach/elph/__init__.py
qmeq/approach/elph/c_redfield.pyx
qmeq/approach/elph/c_pauli.pyx
qmeq/approach/elph/redfield.py
qmeq/approach/elph/c_neumann1.pyx
qmeq/approach/elph/c_neumann1.cpython-39-darwin.so
qmeq/approach/elph/c_lindblad.c
qmeq/approach/elph/c_lindblad.cpython-39-darwin.so
qmeq/approach/elph/c_neumann1.c
qmeq/approach/elph/pauli.py
qmeq/approach/elph/c_pauli.c
qmeq/approach/base/c_RTD.pyx
qmeq/approach/base/c_redfield.c
qmeq/approach/base/c_lindblad.pyx
qmeq/approach/base/c_redfield.cpython-39-darwin.so
qmeq/approach/base/neumann1.py
qmeq/approach/base/c_pauli.cpython-39-darwin.so
qmeq/approach/base/c_RTD.cpython-39-darwin.so
qmeq/approach/base/RTD.py
qmeq/approach/base/c_neumann2.cpython-39-darwin.so
qmeq-1.1.dist-info/LICENSE.md
qmeq-1.1.dist-info/RECORD
qmeq-1.1.dist-info/WHEEL
qmeq-1.1.dist-info/top_level.txt
qmeq-1.1.dist-info/METADATA
