Metadata-Version: 2.1
Name: qmeq
Version: 1.1
Summary: Package for transport calculations in quantum dots using approximate quantum master equations
Home-page: http://github.com/gedaskir/qmeq
Author: Gediminas Kirsanskas
Author-email: qmeq.package@gmail.com
License: BSD 2-Clause
Platform: UNKNOWN
Classifier: Development Status :: 5 - Production/Stable
Classifier: Intended Audience :: Science/Research
Classifier: License :: OSI Approved :: BSD License
Classifier: Operating System :: MacOS
Classifier: Operating System :: Microsoft :: Windows
Classifier: Operating System :: POSIX
Classifier: Operating System :: Unix
Classifier: Programming Language :: Cython
Classifier: Programming Language :: Python :: 3
Classifier: Topic :: Scientific/Engineering :: Physics
License-File: LICENSE.md
Requires-Dist: numpy
Requires-Dist: scipy
